[
    {
        "title": "Home",
        "url": "/index.html",
        "content": "Home Notifications Grupper [[name]] Home Home"
    },
    {
        "title": "Content",
        "url": "/pages/group/content/index.html",
        "content": "Home Notifications Grupper [[name]] Content Content Posts Content"
    },
    {
        "title": "Posts",
        "url": "/pages/group/posts/index.html",
        "content": "Home Notifications Grupper [[name]] Posts Content Posts Posts [[title]] [[content]]"
    },
    {
        "title": "Home",
        "url": "/pages/notifications/index.html",
        "content": "Home Notifications Grupper [[name]] Home Notifieringar Inställningar Nytt för dig Anna commented on a LIA plats Nov 3 Stig approved a LIA plats Nov 3 You have a survey to respond for Javascript 3 Nov 3 Sammy has added a new post in Informationsarkitektur Nov 2 You have 5 new posts in Examensarbete + Tidigare sedda Stig registered a LIA plats Oct 28 You have a survey to respond Oct 25 Sammy has added a new post Oct 22 Ladda fler notifieringar..."
    },
    {
        "title": "Home",
        "url": "/pages/notifications/settings.html",
        "content": "Home Notifications Grupper [[name]] Home Inställningar Vad vill du bli notifierad om? Hur vill du bli notifierad? När vill du bli notifierad?"
    }
]